{"0": {"audio_begin": 142080, "audio_end": 224000}, "1": {"audio_begin": 147200, "audio_end": 229120}, "2": {"audio_begin": 152320, "audio_end": 234240}, "3": {"audio_begin": 157440, "audio_end": 239360}, "4": {"audio_begin": 162560, "audio_end": 244480}, "5": {"audio_begin": 167680, "audio_end": 249600}, "6": {"audio_begin": 172800, "audio_end": 254720}, "7": {"audio_begin": 177920, "audio_end": 259840}, "8": {"audio_begin": 183040, "audio_end": 264960}, "9": {"audio_begin": 188160, "audio_end": 270080}, "10": {"audio_begin": 193280, "audio_end": 275200}, "11": {"audio_begin": 198400, "audio_end": 280320}, "12": {"audio_begin": 203520, "audio_end": 285440}, "13": {"audio_begin": 208640, "audio_end": 290560}, "14": {"audio_begin": 213760, "audio_end": 295680}, "15": {"audio_begin": 218880, "audio_end": 300800}, "16": {"audio_begin": 224000, "audio_end": 305920}, "17": {"audio_begin": 229120, "audio_end": 311040}, "18": {"audio_begin": 234240, "audio_end": 316160}, "19": {"audio_begin": 239360, "audio_end": 321280}, "20": {"audio_begin": 244480, "audio_end": 326400}, "21": {"audio_begin": 249600, "audio_end": 331520}, "22": {"audio_begin": 254720, "audio_end": 336640}, "23": {"audio_begin": 259840, "audio_end": 341760}, "24": {"audio_begin": 264960, "audio_end": 346880}, "25": {"audio_begin": 270080, "audio_end": 352000}, "26": {"audio_begin": 275200, "audio_end": 357120}, "27": {"audio_begin": 280320, "audio_end": 362240}, "28": {"audio_begin": 285440, "audio_end": 367360}, "29": {"audio_begin": 290560, "audio_end": 372480}, "30": {"audio_begin": 295680, "audio_end": 377600}, "31": {"audio_begin": 300800, "audio_end": 382720}, "32": {"audio_begin": 305920, "audio_end": 387840}, "33": {"audio_begin": 311040, "audio_end": 392960}, "34": {"audio_begin": 316160, "audio_end": 398080}, "35": {"audio_begin": 321280, "audio_end": 403200}, "36": {"audio_begin": 326400, "audio_end": 408320}, "37": {"audio_begin": 331520, "audio_end": 413440}, "38": {"audio_begin": 336640, "audio_end": 418560}, "39": {"audio_begin": 341760, "audio_end": 423680}, "40": {"audio_begin": 346880, "audio_end": 428800}, "41": {"audio_begin": 352000, "audio_end": 433920}, "42": {"audio_begin": 357120, "audio_end": 439040}, "43": {"audio_begin": 362240, "audio_end": 444160}, "44": {"audio_begin": 367360, "audio_end": 449280}, "45": {"audio_begin": 372480, "audio_end": 454400}, "46": {"audio_begin": 377600, "audio_end": 459520}, "47": {"audio_begin": 382720, "audio_end": 464640}, "48": {"audio_begin": 387840, "audio_end": 469760}, "49": {"audio_begin": 392960, "audio_end": 474880}, "50": {"audio_begin": 398080, "audio_end": 480000}, "51": {"audio_begin": 403200, "audio_end": 485120}, "52": {"audio_begin": 408320, "audio_end": 490240}, "53": {"audio_begin": 413440, "audio_end": 495360}, "54": {"audio_begin": 418560, "audio_end": 500480}, "55": {"audio_begin": 423680, "audio_end": 505600}, "56": {"audio_begin": 428800, "audio_end": 510720}, "57": {"audio_begin": 433920, "audio_end": 515840}, "58": {"audio_begin": 439040, "audio_end": 520960}, "59": {"audio_begin": 444160, "audio_end": 526080}, "60": {"audio_begin": 449280, "audio_end": 531200}, "61": {"audio_begin": 454400, "audio_end": 536320}, "62": {"audio_begin": 459520, "audio_end": 541440}, "63": {"audio_begin": 464640, "audio_end": 546560}, "64": {"audio_begin": 469760, "audio_end": 551680}, "65": {"audio_begin": 474880, "audio_end": 556800}, "66": {"audio_begin": 480000, "audio_end": 561920}, "67": {"audio_begin": 485120, "audio_end": 567040}, "68": {"audio_begin": 490240, "audio_end": 572160}, "69": {"audio_begin": 495360, "audio_end": 577280}, "70": {"audio_begin": 500480, "audio_end": 582400}, "71": {"audio_begin": 505600, "audio_end": 587520}, "72": {"audio_begin": 510720, "audio_end": 592640}, "73": {"audio_begin": 515840, "audio_end": 597760}, "74": {"audio_begin": 520960, "audio_end": 602880}, "75": {"audio_begin": 526080, "audio_end": 608000}, "76": {"audio_begin": 531200, "audio_end": 613120}, "77": {"audio_begin": 536320, "audio_end": 618240}, "78": {"audio_begin": 541440, "audio_end": 623360}, "79": {"audio_begin": 546560, "audio_end": 628480}, "80": {"audio_begin": 551680, "audio_end": 633600}, "81": {"audio_begin": 556800, "audio_end": 638720}, "82": {"audio_begin": 561920, "audio_end": 643840}, "83": {"audio_begin": 567040, "audio_end": 648960}, "84": {"audio_begin": 572160, "audio_end": 654080}, "85": {"audio_begin": 577280, "audio_end": 659200}, "86": {"audio_begin": 582400, "audio_end": 664320}, "87": {"audio_begin": 587520, "audio_end": 669440}, "88": {"audio_begin": 592640, "audio_end": 674560}, "89": {"audio_begin": 597760, "audio_end": 679680}, "90": {"audio_begin": 602880, "audio_end": 684800}, "91": {"audio_begin": 608000, "audio_end": 689920}, "92": {"audio_begin": 613120, "audio_end": 695040}, "93": {"audio_begin": 618240, "audio_end": 700160}, "94": {"audio_begin": 623360, "audio_end": 705280}, "95": {"audio_begin": 628480, "audio_end": 710400}, "96": {"audio_begin": 633600, "audio_end": 715520}, "97": {"audio_begin": 638720, "audio_end": 720640}, "98": {"audio_begin": 643840, "audio_end": 725760}, "99": {"audio_begin": 648960, "audio_end": 730880}, "100": {"audio_begin": 654080, "audio_end": 736000}, "101": {"audio_begin": 659200, "audio_end": 741120}, "102": {"audio_begin": 664320, "audio_end": 746240}, "103": {"audio_begin": 669440, "audio_end": 751360}, "104": {"audio_begin": 674560, "audio_end": 756480}, "105": {"audio_begin": 679680, "audio_end": 761600}, "106": {"audio_begin": 684800, "audio_end": 766720}, "107": {"audio_begin": 689920, "audio_end": 771840}, "108": {"audio_begin": 695040, "audio_end": 776960}, "109": {"audio_begin": 700160, "audio_end": 782080}, "110": {"audio_begin": 705280, "audio_end": 787200}, "111": {"audio_begin": 710400, "audio_end": 792320}, "112": {"audio_begin": 715520, "audio_end": 797440}, "113": {"audio_begin": 720640, "audio_end": 802560}, "114": {"audio_begin": 725760, "audio_end": 807680}, "115": {"audio_begin": 730880, "audio_end": 812800}, "116": {"audio_begin": 736000, "audio_end": 817920}, "117": {"audio_begin": 741120, "audio_end": 823040}, "118": {"audio_begin": 746240, "audio_end": 828160}, "119": {"audio_begin": 751360, "audio_end": 833280}, "120": {"audio_begin": 756480, "audio_end": 838400}, "121": {"audio_begin": 761600, "audio_end": 843520}, "122": {"audio_begin": 766720, "audio_end": 848640}, "123": {"audio_begin": 771840, "audio_end": 853760}, "124": {"audio_begin": 776960, "audio_end": 858880}, "125": {"audio_begin": 782080, "audio_end": 864000}, "126": {"audio_begin": 787200, "audio_end": 869120}, "127": {"audio_begin": 792320, "audio_end": 874240}, "128": {"audio_begin": 797440, "audio_end": 879360}, "129": {"audio_begin": 802560, "audio_end": 884480}, "130": {"audio_begin": 807680, "audio_end": 889600}, "131": {"audio_begin": 812800, "audio_end": 894720}, "132": {"audio_begin": 817920, "audio_end": 899840}, "133": {"audio_begin": 823040, "audio_end": 904960}, "134": {"audio_begin": 828160, "audio_end": 910080}, "135": {"audio_begin": 833280, "audio_end": 915200}, "136": {"audio_begin": 838400, "audio_end": 920320}, "137": {"audio_begin": 843520, "audio_end": 925440}, "138": {"audio_begin": 848640, "audio_end": 930560}, "139": {"audio_begin": 853760, "audio_end": 935680}, "140": {"audio_begin": 858880, "audio_end": 940800}, "141": {"audio_begin": 864000, "audio_end": 945920}, "142": {"audio_begin": 869120, "audio_end": 951040}, "143": {"audio_begin": 874240, "audio_end": 956160}, "144": {"audio_begin": 879360, "audio_end": 961280}, "145": {"audio_begin": 884480, "audio_end": 966400}, "146": {"audio_begin": 889600, "audio_end": 971520}, "147": {"audio_begin": 894720, "audio_end": 976640}, "148": {"audio_begin": 899840, "audio_end": 981760}, "149": {"audio_begin": 904960, "audio_end": 986880}, "150": {"audio_begin": 910080, "audio_end": 992000}, "151": {"audio_begin": 915200, "audio_end": 997120}, "152": {"audio_begin": 920320, "audio_end": 1002240}, "153": {"audio_begin": 925440, "audio_end": 1007360}, "154": {"audio_begin": 930560, "audio_end": 1012480}, "155": {"audio_begin": 935680, "audio_end": 1017600}, "156": {"audio_begin": 940800, "audio_end": 1022720}, "157": {"audio_begin": 945920, "audio_end": 1027840}, "158": {"audio_begin": 951040, "audio_end": 1032960}, "159": {"audio_begin": 956160, "audio_end": 1038080}, "160": {"audio_begin": 961280, "audio_end": 1043200}, "161": {"audio_begin": 966400, "audio_end": 1048320}, "162": {"audio_begin": 971520, "audio_end": 1053440}, "163": {"audio_begin": 976640, "audio_end": 1058560}, "164": {"audio_begin": 981760, "audio_end": 1063680}, "165": {"audio_begin": 986880, "audio_end": 1068800}, "166": {"audio_begin": 992000, "audio_end": 1073920}, "167": {"audio_begin": 997120, "audio_end": 1079040}, "168": {"audio_begin": 1002240, "audio_end": 1084160}, "169": {"audio_begin": 1007360, "audio_end": 1089280}, "170": {"audio_begin": 1012480, "audio_end": 1094400}, "171": {"audio_begin": 1017600, "audio_end": 1099520}, "172": {"audio_begin": 1022720, "audio_end": 1104640}, "173": {"audio_begin": 1027840, "audio_end": 1109760}, "174": {"audio_begin": 1032960, "audio_end": 1114880}, "175": {"audio_begin": 1038080, "audio_end": 1120000}, "176": {"audio_begin": 1043200, "audio_end": 1125120}, "177": {"audio_begin": 1048320, "audio_end": 1130240}, "178": {"audio_begin": 1053440, "audio_end": 1135360}, "179": {"audio_begin": 1058560, "audio_end": 1140480}, "180": {"audio_begin": 1063680, "audio_end": 1145600}, "181": {"audio_begin": 1068800, "audio_end": 1150720}, "182": {"audio_begin": 1073920, "audio_end": 1155840}, "183": {"audio_begin": 1079040, "audio_end": 1160960}, "184": {"audio_begin": 1084160, "audio_end": 1166080}, "185": {"audio_begin": 1089280, "audio_end": 1171200}, "186": {"audio_begin": 1094400, "audio_end": 1176320}, "187": {"audio_begin": 1099520, "audio_end": 1181440}, "188": {"audio_begin": 1104640, "audio_end": 1186560}, "189": {"audio_begin": 1109760, "audio_end": 1191680}, "190": {"audio_begin": 1114880, "audio_end": 1196800}, "191": {"audio_begin": 1120000, "audio_end": 1201920}, "192": {"audio_begin": 1125120, "audio_end": 1207040}, "193": {"audio_begin": 1130240, "audio_end": 1212160}, "194": {"audio_begin": 1135360, "audio_end": 1217280}, "195": {"audio_begin": 1140480, "audio_end": 1222400}, "196": {"audio_begin": 1145600, "audio_end": 1227520}, "197": {"audio_begin": 1150720, "audio_end": 1232640}, "198": {"audio_begin": 1155840, "audio_end": 1237760}, "199": {"audio_begin": 1160960, "audio_end": 1242880}, "200": {"audio_begin": 1166080, "audio_end": 1248000}, "201": {"audio_begin": 1171200, "audio_end": 1253120}, "202": {"audio_begin": 1176320, "audio_end": 1258240}, "203": {"audio_begin": 1181440, "audio_end": 1263360}, "204": {"audio_begin": 1186560, "audio_end": 1268480}, "205": {"audio_begin": 1191680, "audio_end": 1273600}, "206": {"audio_begin": 1196800, "audio_end": 1278720}, "207": {"audio_begin": 1201920, "audio_end": 1283840}, "208": {"audio_begin": 1207040, "audio_end": 1288960}, "209": {"audio_begin": 1212160, "audio_end": 1294080}, "210": {"audio_begin": 1217280, "audio_end": 1299200}, "211": {"audio_begin": 1222400, "audio_end": 1304320}, "212": {"audio_begin": 1227520, "audio_end": 1309440}, "213": {"audio_begin": 1232640, "audio_end": 1314560}, "214": {"audio_begin": 1237760, "audio_end": 1319680}, "215": {"audio_begin": 1242880, "audio_end": 1324800}, "216": {"audio_begin": 1248000, "audio_end": 1329920}, "217": {"audio_begin": 1253120, "audio_end": 1335040}, "218": {"audio_begin": 1258240, "audio_end": 1340160}, "219": {"audio_begin": 1263360, "audio_end": 1345280}, "220": {"audio_begin": 1268480, "audio_end": 1350400}, "221": {"audio_begin": 1273600, "audio_end": 1355520}, "222": {"audio_begin": 1278720, "audio_end": 1360640}, "223": {"audio_begin": 1283840, "audio_end": 1365760}, "224": {"audio_begin": 1288960, "audio_end": 1370880}, "225": {"audio_begin": 1294080, "audio_end": 1376000}, "226": {"audio_begin": 1299200, "audio_end": 1381120}, "227": {"audio_begin": 1304320, "audio_end": 1386240}, "228": {"audio_begin": 1309440, "audio_end": 1391360}, "229": {"audio_begin": 1314560, "audio_end": 1396480}, "230": {"audio_begin": 1319680, "audio_end": 1401600}, "231": {"audio_begin": 1324800, "audio_end": 1406720}, "232": {"audio_begin": 1329920, "audio_end": 1411840}, "233": {"audio_begin": 1335040, "audio_end": 1416960}, "234": {"audio_begin": 1340160, "audio_end": 1422080}, "235": {"audio_begin": 1345280, "audio_end": 1427200}, "236": {"audio_begin": 1350400, "audio_end": 1432320}, "237": {"audio_begin": 1355520, "audio_end": 1437440}, "238": {"audio_begin": 1360640, "audio_end": 1442560}, "239": {"audio_begin": 1365760, "audio_end": 1447680}, "240": {"audio_begin": 1370880, "audio_end": 1452800}, "241": {"audio_begin": 1376000, "audio_end": 1457920}, "242": {"audio_begin": 1381120, "audio_end": 1463040}, "243": {"audio_begin": 1386240, "audio_end": 1468160}, "244": {"audio_begin": 1391360, "audio_end": 1473280}, "245": {"audio_begin": 1396480, "audio_end": 1478400}, "246": {"audio_begin": 1401600, "audio_end": 1483520}, "247": {"audio_begin": 1406720, "audio_end": 1488640}, "248": {"audio_begin": 1411840, "audio_end": 1493760}, "249": {"audio_begin": 1416960, "audio_end": 1498880}, "250": {"audio_begin": 1422080, "audio_end": 1504000}, "251": {"audio_begin": 1427200, "audio_end": 1509120}, "252": {"audio_begin": 1432320, "audio_end": 1514240}, "253": {"audio_begin": 1437440, "audio_end": 1519360}, "254": {"audio_begin": 1442560, "audio_end": 1524480}, "255": {"audio_begin": 1447680, "audio_end": 1529600}, "256": {"audio_begin": 1452800, "audio_end": 1534720}, "257": {"audio_begin": 1457920, "audio_end": 1539840}, "258": {"audio_begin": 1463040, "audio_end": 1544960}, "259": {"audio_begin": 1468160, "audio_end": 1550080}, "260": {"audio_begin": 1473280, "audio_end": 1555200}, "261": {"audio_begin": 1478400, "audio_end": 1560320}, "262": {"audio_begin": 1483520, "audio_end": 1565440}, "263": {"audio_begin": 1488640, "audio_end": 1570560}, "264": {"audio_begin": 1493760, "audio_end": 1575680}, "265": {"audio_begin": 1498880, "audio_end": 1580800}, "266": {"audio_begin": 1504000, "audio_end": 1585920}, "267": {"audio_begin": 1509120, "audio_end": 1591040}, "268": {"audio_begin": 1514240, "audio_end": 1596160}, "269": {"audio_begin": 1519360, "audio_end": 1601280}, "270": {"audio_begin": 1524480, "audio_end": 1606400}, "271": {"audio_begin": 1529600, "audio_end": 1611520}, "272": {"audio_begin": 1534720, "audio_end": 1616640}, "273": {"audio_begin": 1539840, "audio_end": 1621760}, "274": {"audio_begin": 1544960, "audio_end": 1626880}, "275": {"audio_begin": 1550080, "audio_end": 1632000}, "276": {"audio_begin": 1555200, "audio_end": 1637120}, "277": {"audio_begin": 1560320, "audio_end": 1642240}, "278": {"audio_begin": 1565440, "audio_end": 1647360}, "279": {"audio_begin": 1570560, "audio_end": 1652480}, "280": {"audio_begin": 1575680, "audio_end": 1657600}, "281": {"audio_begin": 1580800, "audio_end": 1662720}, "282": {"audio_begin": 1585920, "audio_end": 1667840}, "283": {"audio_begin": 1591040, "audio_end": 1672960}, "284": {"audio_begin": 1596160, "audio_end": 1678080}, "285": {"audio_begin": 1601280, "audio_end": 1683200}, "286": {"audio_begin": 1606400, "audio_end": 1688320}, "287": {"audio_begin": 1611520, "audio_end": 1693440}, "288": {"audio_begin": 1616640, "audio_end": 1698560}, "289": {"audio_begin": 1621760, "audio_end": 1703680}, "290": {"audio_begin": 1626880, "audio_end": 1708800}, "291": {"audio_begin": 1632000, "audio_end": 1713920}, "292": {"audio_begin": 1637120, "audio_end": 1719040}, "293": {"audio_begin": 1642240, "audio_end": 1724160}, "294": {"audio_begin": 1647360, "audio_end": 1729280}, "295": {"audio_begin": 1652480, "audio_end": 1734400}, "296": {"audio_begin": 1657600, "audio_end": 1739520}, "297": {"audio_begin": 1662720, "audio_end": 1744640}, "298": {"audio_begin": 1667840, "audio_end": 1749760}, "299": {"audio_begin": 1672960, "audio_end": 1754880}, "300": {"audio_begin": 1678080, "audio_end": 1760000}, "301": {"audio_begin": 1683200, "audio_end": 1765120}, "302": {"audio_begin": 1688320, "audio_end": 1770240}, "303": {"audio_begin": 1693440, "audio_end": 1775360}, "304": {"audio_begin": 1698560, "audio_end": 1780480}, "305": {"audio_begin": 1703680, "audio_end": 1785600}, "306": {"audio_begin": 1708800, "audio_end": 1790720}, "307": {"audio_begin": 1713920, "audio_end": 1795840}, "308": {"audio_begin": 1719040, "audio_end": 1800960}, "309": {"audio_begin": 1724160, "audio_end": 1806080}, "310": {"audio_begin": 1729280, "audio_end": 1811200}, "311": {"audio_begin": 1734400, "audio_end": 1816320}, "312": {"audio_begin": 1739520, "audio_end": 1821440}, "313": {"audio_begin": 1744640, "audio_end": 1826560}, "314": {"audio_begin": 1749760, "audio_end": 1831680}, "315": {"audio_begin": 1754880, "audio_end": 1836800}, "316": {"audio_begin": 1760000, "audio_end": 1841920}, "317": {"audio_begin": 1765120, "audio_end": 1847040}, "318": {"audio_begin": 1770240, "audio_end": 1852160}, "319": {"audio_begin": 1775360, "audio_end": 1857280}, "320": {"audio_begin": 1780480, "audio_end": 1862400}, "321": {"audio_begin": 1785600, "audio_end": 1867520}, "322": {"audio_begin": 1790720, "audio_end": 1872640}, "323": {"audio_begin": 1795840, "audio_end": 1877760}, "324": {"audio_begin": 1800960, "audio_end": 1882880}, "325": {"audio_begin": 1806080, "audio_end": 1888000}, "326": {"audio_begin": 1811200, "audio_end": 1893120}, "327": {"audio_begin": 1816320, "audio_end": 1898240}, "328": {"audio_begin": 1821440, "audio_end": 1903360}, "329": {"audio_begin": 1826560, "audio_end": 1908480}, "330": {"audio_begin": 1831680, "audio_end": 1913600}}